savage/__init__.py
savage/graphic.py
savage/__pycache__/__init__.cpython-39.pyc
savage/__pycache__/graphic.cpython-39.pyc
savage/elements/__init__.py
savage/elements/element.py
savage/elements/group.py
savage/elements/text.py
savage/elements/__pycache__/__init__.cpython-39.pyc
savage/elements/__pycache__/circle.cpython-39.pyc
savage/elements/__pycache__/element.cpython-39.pyc
savage/elements/__pycache__/ellipse.cpython-39.pyc
savage/elements/__pycache__/group.cpython-39.pyc
savage/elements/__pycache__/line.cpython-39.pyc
savage/elements/__pycache__/rect.cpython-39.pyc
savage/elements/__pycache__/text.cpython-39.pyc
savage/elements/shapes/__init__.py
savage/elements/shapes/circle.py
savage/elements/shapes/ellipse.py
savage/elements/shapes/line.py
savage/elements/shapes/polygon.py
savage/elements/shapes/polyline.py
savage/elements/shapes/rect.py
savage/elements/shapes/shape.py
savage/elements/shapes/__pycache__/__init__.cpython-39.pyc
savage/elements/shapes/__pycache__/circle.cpython-39.pyc
savage/elements/shapes/__pycache__/ellipse.cpython-39.pyc
savage/elements/shapes/__pycache__/line.cpython-39.pyc
savage/elements/shapes/__pycache__/polygon.cpython-39.pyc
savage/elements/shapes/__pycache__/polyline.cpython-39.pyc
savage/elements/shapes/__pycache__/rect.cpython-39.pyc
savage/elements/shapes/__pycache__/shape.cpython-39.pyc
savage_generator-0.1.3.dist-info/METADATA
savage_generator-0.1.3.dist-info/WHEEL
savage_generator-0.1.3.dist-info/top_level.txt
savage_generator-0.1.3.dist-info/RECORD
