Metadata-Version: 2.4
Name: savage-generator
Version: 0.1.3
Summary: A basic SVG generator in Python
Author-email: Jamie Gillett <jamie.gillett@gmail.com>
Project-URL: Homepage, https://github.com/jamie-gillett/savage
Project-URL: Issues, https://github.com/jamie-gillett/savage/issues
Classifier: Programming Language :: Python :: 3
Classifier: Operating System :: OS Independent
Requires-Python: >=3.6
Provides-Extra: dev
Requires-Dist: pytest>=7.0; extra == "dev"
Requires-Dist: pytest-mock>=3.0; extra == "dev"
Requires-Dist: pytest-cov>=3.0; extra == "dev"
